wsgi_basic_auth.py
wsgi_django_media.py
wsgi_django_media-1.0.0.dist-info/DESCRIPTION.rst
wsgi_django_media-1.0.0.dist-info/METADATA
wsgi_django_media-1.0.0.dist-info/RECORD
wsgi_django_media-1.0.0.dist-info/WHEEL
wsgi_django_media-1.0.0.dist-info/metadata.json
wsgi_django_media-1.0.0.dist-info/top_level.txt
