Metadata-Version: 2.0
Name: wsgi-django-media
Version: 1.0.0
Summary: WSGI middleware to serve media for faster Django development
Home-page: https://github.com/mvantellingen/wsgi-django-media
Author: Michael van Tellingen
Author-email: michaelvantellingen@gmail.com
License: MIT
Platform: UNKNOWN
Classifier: Development Status :: 5 - Production/Stable
Classifier: License :: OSI Approved :: MIT License
Classifier: Programming Language :: Python :: 2
Classifier: Programming Language :: Python :: 2.7
Classifier: Programming Language :: Python :: 3
Classifier: Programming Language :: Python :: 3.3
Classifier: Programming Language :: Python :: 3.4
Classifier: Programming Language :: Python :: 3.5
Classifier: Programming Language :: Python :: 3.6
Classifier: Programming Language :: Python :: Implementation :: CPython
Classifier: Programming Language :: Python :: Implementation :: PyPy
Provides-Extra: docs
Provides-Extra: test
Requires-Dist: django (>=1.8)
Requires-Dist: webob (>=1.0.0)
Provides-Extra: docs
Requires-Dist: sphinx (>=1.4.0); extra == 'docs'
Provides-Extra: test
Requires-Dist: pytest-cov (>=2.2.0); extra == 'test'
Requires-Dist: pytest-django (>=3.0.0); extra == 'test'
Requires-Dist: pytest (>=2.8.3); extra == 'test'
Requires-Dist: WebTest (==2.0.23); extra == 'test'
Requires-Dist: isort (==4.2.5); extra == 'test'
Requires-Dist: flake8 (==3.0.3); extra == 'test'
Requires-Dist: flake8-blind-except (==0.1.1); extra == 'test'
Requires-Dist: flake8-debugger (==1.4.0); extra == 'test'
